.gitignore
LICENSE
README.md
setup.py
sleekdigda/__init__.py
sleekdigda/digda.py
sleekdigda/errors.py
sleekdigda/forward.py
sleekdigda/stanza.py
sleekdigda.egg-info/PKG-INFO
sleekdigda.egg-info/SOURCES.txt
sleekdigda.egg-info/dependency_links.txt
sleekdigda.egg-info/requires.txt
sleekdigda.egg-info/top_level.txt