Metadata-Version: 1.0
Name: sleekdigda
Version: 0.2.0
Summary: XEP-Digda - SleekXMPP plugin
Home-page: UNKNOWN
Author: Optiflows R&D
Author-email: rand@optiflows.com
License: UNKNOWN
Platform: UNKNOWN
